{
    "FastScanner.next()#b#311": [
        "65",
        "66"
    ],
    "FastScanner.next()#b#312": [
        "65",
        "32",
        "66",
        "10"
    ],
    "FastScanner.next()#b#313": [
        "65",
        "66"
    ],
    "FastScanner.next()#b#314": [
        "32",
        "10"
    ],
    "Main.solve()#X#26": [
        "A"
    ],
    "Main.solve()#Y#27": [
        "B"
    ],
    "Main.solve()#ans#28": [
        "\""
    ],
    "Main.solve()#X#29": [
        "A"
    ],
    "Main.solve()#Y#29": [
        "B"
    ],
    "Main.solve()#ans#30": [
        "\"<\""
    ]
}