{
    "2": {
        "count": 0
    },
    "3": {
        "new_text": []
    },
    "4": {
        "char": "x",
        "text": "DSUWeqExTQdCMGpqur"
    },
    "5": {
        "char": "x",
        "lower": "a",
        "upper": "x"
    },
    "6": {
        "char": "x"
    },
    "8": {
        "new_text": [
            "x",
            "x",
            "x",
            "x",
            "x",
            "x",
            "x",
            "x",
            "x",
            "x",
            "x",
            "x",
            "x",
            "x",
            "x",
            "x",
            "x",
            "x"
        ],
        "char": "x"
    },
    "9": {
        "count": 0,
        "new_text": [
            "x",
            "x",
            "x",
            "x",
            "x",
            "x",
            "x",
            "x",
            "x",
            "x",
            "x",
            "x",
            "x",
            "x",
            "x",
            "x",
            "x",
            "x"
        ]
    }
}