{
    "5": [
        "sc",
        "System"
    ],
    "6": [
        "sc",
        "A"
    ],
    "7": [
        "sc",
        "B"
    ],
    "8": [
        "sc",
        "C"
    ],
    "9": [
        "sc",
        "D"
    ],
    "10": [
        "sc",
        "E"
    ],
    "11": [
        "sc",
        "F"
    ],
    "12": [
        "ans1",
        "A"
    ],
    "13": [
        "ans2"
    ],
    "14": [
        "F",
        "a",
        "A"
    ],
    "15": [
        "F",
        "b",
        "B"
    ],
    "16": [
        "F",
        "c",
        "C"
    ],
    "17": [
        "d",
        "F",
        "D"
    ],
    "18": [
        "A",
        "b",
        "D",
        "d",
        "E",
        "a",
        "C",
        "F",
        "c",
        "B"
    ],
    "19": [
        "a",
        "b"
    ],
    "20": [
        "ans1",
        "ans2",
        "D",
        "A",
        "b",
        "d",
        "a",
        "C",
        "c",
        "B"
    ],
    "21": [
        "ans1",
        "A",
        "b",
        "D",
        "d",
        "a",
        "C",
        "c",
        "B"
    ],
    "22": [
        "D",
        "ans2",
        "d",
        "C",
        "c"
    ],
    "29": [
        "ans1",
        "ans2",
        "System"
    ]
}