{
    "129": [
        "nl"
    ],
    "132": [
        "n",
        "a"
    ],
    "133": [
        "n",
        "i"
    ],
    "134": [
        "i",
        "a"
    ],
    "136": [
        "a"
    ],
    "139": [
        "n",
        "a"
    ],
    "12": [
        "sc"
    ],
    "140": [
        "n",
        "i"
    ],
    "141": [
        "i",
        "a"
    ],
    "14": [
        "n",
        "sc"
    ],
    "15": [
        "k",
        "sc"
    ],
    "143": [
        "a"
    ],
    "17": [
        "k",
        "n",
        "System"
    ],
    "146": [
        "Double"
    ],
    "24": [
        "n"
    ],
    "25": [
        "n"
    ],
    "26": [
        "mod"
    ],
    "27": [
        "k",
        "n"
    ],
    "28": [
        "k",
        "n",
        "dp"
    ],
    "29": [
        "dp"
    ],
    "30": [
        "n",
        "i"
    ],
    "31": [
        "dp",
        "i"
    ],
    "33": [
        "k",
        "i"
    ],
    "34": [
        "dp",
        "i"
    ],
    "35": [
        "dp",
        "i"
    ],
    "38": [
        "n",
        "i"
    ],
    "39": [
        "k",
        "j"
    ],
    "40": [
        "j",
        "i"
    ],
    "41": [
        "j",
        "dp",
        "i"
    ],
    "42": [
        "mod",
        "j",
        "dp",
        "i"
    ],
    "45": [
        "j",
        "dp",
        "i"
    ],
    "50": [
        "k",
        "n",
        "dp"
    ],
    "55": [
        "System"
    ],
    "60": [
        "buflen",
        "ptr"
    ],
    "63": [
        "ptr"
    ],
    "65": [
        "in",
        "buffer",
        "buflen"
    ],
    "67": [
        "e"
    ],
    "69": [
        "buflen"
    ],
    "77": [
        "buffer",
        "ptr"
    ],
    "82": [
        "c"
    ],
    "85": [
        "buffer",
        "ptr"
    ],
    "86": [
        "ptr"
    ],
    "92": [
        "sb"
    ],
    "93": [
        "b"
    ],
    "94": [
        "b"
    ],
    "95": [
        "b",
        "sb"
    ],
    "96": [
        "b"
    ],
    "98": [
        "sb"
    ],
    "103": [
        "n"
    ],
    "104": [
        "minus"
    ],
    "105": [
        "b"
    ],
    "106": [
        "b"
    ],
    "107": [
        "minus"
    ],
    "108": [
        "b"
    ],
    "110": [
        "b"
    ],
    "114": [
        "b"
    ],
    "115": [
        "n"
    ],
    "116": [
        "n",
        "b"
    ],
    "117": [
        "b"
    ],
    "118": [
        "n",
        "minus"
    ],
    "122": [
        "b"
    ],
    "126": [
        "nl"
    ],
    "127": [
        "Integer",
        "nl"
    ]
}