{
    "14": [
        "Integer"
    ],
    "18": [
        "n"
    ],
    "19": [
        "m"
    ],
    "20": [
        "k"
    ],
    "21": [
        "mod"
    ],
    "22": [
        "mod",
        "fif"
    ],
    "24": [
        "xsum"
    ],
    "25": [
        "ysum"
    ],
    "27": [
        "xa",
        "k",
        "fif",
        "mod",
        "n",
        "m"
    ],
    "28": [
        "xb"
    ],
    "29": [
        "i",
        "m"
    ],
    "30": [
        "i",
        "mod",
        "n",
        "tmp",
        "m"
    ],
    "31": [
        "tmp",
        "xb"
    ],
    "32": [
        "mod",
        "xb"
    ],
    "34": [
        "xa",
        "k",
        "fif",
        "xc",
        "mod",
        "xb"
    ],
    "35": [
        "fif",
        "k",
        "xc",
        "mod",
        "xsum"
    ],
    "39": [
        "k",
        "fif",
        "mod",
        "ya",
        "n",
        "m"
    ],
    "40": [
        "yb"
    ],
    "41": [
        "i",
        "n"
    ],
    "42": [
        "i",
        "mod",
        "n",
        "tmp",
        "m"
    ],
    "43": [
        "yb",
        "tmp"
    ],
    "44": [
        "mod",
        "yb"
    ],
    "46": [
        "k",
        "fif",
        "mod",
        "yb",
        "ya",
        "yc"
    ],
    "47": [
        "ysum",
        "fif",
        "k",
        "mod",
        "yc"
    ],
    "51": [
        "mod",
        "out",
        "xsum",
        "ysum"
    ],
    "56": [
        "n",
        "r"
    ],
    "58": [
        "n",
        "fif",
        "r",
        "mod"
    ],
    "63": [
        "n",
        "f"
    ],
    "64": [
        "n",
        "invf"
    ],
    "65": [
        "f"
    ],
    "66": [
        "i",
        "n"
    ],
    "67": [
        "i",
        "mod",
        "f"
    ],
    "69": [
        "n",
        "a",
        "f"
    ],
    "70": [
        "mod",
        "b"
    ],
    "71": [
        "p",
        "q"
    ],
    "72": [
        "b"
    ],
    "73": [
        "a",
        "c",
        "b"
    ],
    "74": [
        "d"
    ],
    "75": [
        "d",
        "a"
    ],
    "76": [
        "a",
        "b"
    ],
    "77": [
        "d",
        "b"
    ],
    "78": [
        "d",
        "p"
    ],
    "79": [
        "p",
        "q"
    ],
    "80": [
        "d",
        "c",
        "q"
    ],
    "82": [
        "n",
        "mod",
        "p",
        "invf"
    ],
    "83": [
        "i",
        "n"
    ],
    "84": [
        "i",
        "mod",
        "invf"
    ],
    "86": [
        "invf",
        "f"
    ],
    "92": [
        "System",
        "is",
        "INPUT"
    ],
    "93": [
        "System",
        "out"
    ],
    "94": [
        "s",
        "System"
    ],
    "96": [
        "out"
    ],
    "97": [
        "s",
        "System",
        "INPUT"
    ],
    "107": [
        "lenbuf"
    ],
    "108": [
        "ptrbuf",
        "lenbuf"
    ],
    "109": [
        "ptrbuf"
    ],
    "110": [
        "inbuf",
        "lenbuf",
        "is"
    ],
    "111": [
        "lenbuf"
    ],
    "113": [
        "ptrbuf",
        "inbuf"
    ],
    "116": [
        "c"
    ],
    "117": [
        "b"
    ],
    "119": [
        "Double"
    ],
    "124": [
        "b"
    ],
    "125": [
        "sb"
    ],
    "126": [
        "b"
    ],
    "127": [
        "sb",
        "b"
    ],
    "128": [
        "b"
    ],
    "130": [
        "sb"
    ],
    "135": [
        "buf",
        "n"
    ],
    "136": [
        "p",
        "b"
    ],
    "137": [
        "n",
        "p",
        "b"
    ],
    "138": [
        "buf",
        "p",
        "b"
    ],
    "139": [
        "b"
    ],
    "141": [
        "buf",
        "n",
        "p",
        "Arrays"
    ],
    "146": [
        "map",
        "n"
    ],
    "147": [
        "map",
        "i",
        "m",
        "n"
    ],
    "148": [
        "map"
    ],
    "153": [
        "n",
        "a"
    ],
    "154": [
        "i",
        "a",
        "n"
    ],
    "155": [
        "a"
    ],
    "160": [
        "b",
        "num"
    ],
    "161": [
        "minus"
    ],
    "162": [
        "b"
    ],
    "163": [
        "b"
    ],
    "164": [
        "minus"
    ],
    "165": [
        "b"
    ],
    "169": [
        "b"
    ],
    "170": [
        "b",
        "num"
    ],
    "172": [
        "minus",
        "num"
    ],
    "174": [
        "b"
    ],
    "180": [
        "num"
    ],
    "181": [
        "b"
    ],
    "182": [
        "minus"
    ],
    "183": [
        "b"
    ],
    "184": [
        "b"
    ],
    "185": [
        "minus"
    ],
    "186": [
        "b"
    ],
    "190": [
        "b"
    ],
    "191": [
        "b",
        "num"
    ],
    "193": [
        "minus",
        "num"
    ],
    "195": [
        "b"
    ],
    "199": [
        "o",
        "System",
        "Arrays"
    ]
}