{
    "0": {
        "line_number": 4,
        "method": "Main.main()",
        "variables": {}
    },
    "1": {
        "line_number": 5,
        "method": "Main.main()",
        "variables": {
            "a": "3"
        }
    },
    "2": {
        "line_number": 6,
        "method": "Main.main()",
        "variables": {
            "a": "3",
            "b": "0"
        }
    },
    "3": {
        "line_number": 7,
        "method": "Main.main()",
        "variables": {
            "a": "3",
            "b": "0",
            "c": "10"
        }
    },
    "4": {
        "line_number": 8,
        "method": "Main.main()",
        "variables": {
            "a": "3",
            "b": "0",
            "c": "10",
            "i": "0",
            "cnt": "0"
        }
    },
    "5": {
        "line_number": 9,
        "method": "Main.main()",
        "variables": {
            "a": "3",
            "b": "0",
            "c": "10",
            "i": "0",
            "cnt": "0"
        }
    },
    "6": {
        "line_number": 10,
        "method": "Main.main()",
        "variables": {
            "a": "3",
            "b": "0",
            "c": "10",
            "i": "1",
            "cnt": "0"
        }
    },
    "7": {
        "line_number": 11,
        "method": "Main.main()",
        "variables": {
            "a": "3",
            "b": "0",
            "c": "10",
            "i": "1",
            "cnt": "3"
        }
    },
    "8": {
        "line_number": 12,
        "method": "Main.main()",
        "variables": {
            "a": "3",
            "b": "0",
            "c": "10",
            "i": "1",
            "cnt": "3"
        }
    },
    "9": {
        "line_number": 9,
        "method": "Main.main()",
        "variables": {
            "a": "3",
            "b": "0",
            "c": "10",
            "i": "1",
            "cnt": "3"
        }
    },
    "10": {
        "line_number": 10,
        "method": "Main.main()",
        "variables": {
            "a": "3",
            "b": "0",
            "c": "10",
            "i": "2",
            "cnt": "3"
        }
    },
    "11": {
        "line_number": 11,
        "method": "Main.main()",
        "variables": {
            "a": "3",
            "b": "0",
            "c": "10",
            "i": "2",
            "cnt": "6"
        }
    },
    "12": {
        "line_number": 12,
        "method": "Main.main()",
        "variables": {
            "a": "3",
            "b": "0",
            "c": "10",
            "i": "2",
            "cnt": "6"
        }
    },
    "13": {
        "line_number": 9,
        "method": "Main.main()",
        "variables": {
            "a": "3",
            "b": "0",
            "c": "10",
            "i": "2",
            "cnt": "6"
        }
    },
    "14": {
        "line_number": 10,
        "method": "Main.main()",
        "variables": {
            "a": "3",
            "b": "0",
            "c": "10",
            "i": "3",
            "cnt": "6"
        }
    },
    "15": {
        "line_number": 11,
        "method": "Main.main()",
        "variables": {
            "a": "3",
            "b": "0",
            "c": "10",
            "i": "3",
            "cnt": "9"
        }
    },
    "16": {
        "line_number": 12,
        "method": "Main.main()",
        "variables": {
            "a": "3",
            "b": "0",
            "c": "10",
            "i": "3",
            "cnt": "9"
        }
    },
    "17": {
        "line_number": 9,
        "method": "Main.main()",
        "variables": {
            "a": "3",
            "b": "0",
            "c": "10",
            "i": "3",
            "cnt": "9"
        }
    },
    "18": {
        "line_number": 10,
        "method": "Main.main()",
        "variables": {
            "a": "3",
            "b": "0",
            "c": "10",
            "i": "4",
            "cnt": "9"
        }
    },
    "19": {
        "line_number": 11,
        "method": "Main.main()",
        "variables": {
            "a": "3",
            "b": "0",
            "c": "10",
            "i": "4",
            "cnt": "12"
        }
    },
    "20": {
        "line_number": 12,
        "method": "Main.main()",
        "variables": {
            "a": "3",
            "b": "0",
            "c": "10",
            "i": "4",
            "cnt": "12"
        }
    },
    "21": {
        "line_number": 9,
        "method": "Main.main()",
        "variables": {
            "a": "3",
            "b": "0",
            "c": "10",
            "i": "4",
            "cnt": "12"
        }
    },
    "22": {
        "line_number": 15,
        "method": "Main.main()",
        "variables": {
            "a": "3",
            "b": "0",
            "c": "10",
            "i": "4",
            "cnt": "12"
        }
    }
}