{
    "0": {
        "line_number": 10,
        "method": "Main.main()",
        "variables": {}
    },
    "1": {
        "line_number": 28,
        "method": "Main$Scanner.<init>()",
        "variables": {}
    },
    "2": {
        "line_number": 29,
        "method": "Main$Scanner.<init>()",
        "variables": {}
    },
    "3": {
        "line_number": 30,
        "method": "Main$Scanner.<init>()",
        "variables": {}
    },
    "4": {
        "line_number": 10,
        "method": "Main.main()",
        "variables": {}
    },
    "5": {
        "line_number": 11,
        "method": "Main.main()",
        "variables": {}
    },
    "6": {
        "line_number": 12,
        "method": "Main.main()",
        "variables": {}
    },
    "7": {
        "line_number": 40,
        "method": "Main$Scanner.nextInt()",
        "variables": {}
    },
    "8": {
        "line_number": 32,
        "method": "Main$Scanner.next()",
        "variables": {}
    },
    "9": {
        "line_number": 33,
        "method": "Main$Scanner.next()",
        "variables": {}
    },
    "10": {
        "line_number": 32,
        "method": "Main$Scanner.next()",
        "variables": {}
    },
    "11": {
        "line_number": 34,
        "method": "Main$Scanner.next()",
        "variables": {}
    },
    "12": {
        "line_number": 40,
        "method": "Main$Scanner.nextInt()",
        "variables": {}
    },
    "13": {
        "line_number": 12,
        "method": "Main.main()",
        "variables": {}
    },
    "14": {
        "line_number": 40,
        "method": "Main$Scanner.nextInt()",
        "variables": {}
    },
    "15": {
        "line_number": 32,
        "method": "Main$Scanner.next()",
        "variables": {}
    },
    "16": {
        "line_number": 34,
        "method": "Main$Scanner.next()",
        "variables": {}
    },
    "17": {
        "line_number": 40,
        "method": "Main$Scanner.nextInt()",
        "variables": {
            "n": "5"
        }
    },
    "18": {
        "line_number": 12,
        "method": "Main.main()",
        "variables": {}
    },
    "19": {
        "line_number": 40,
        "method": "Main$Scanner.nextInt()",
        "variables": {}
    },
    "20": {
        "line_number": 32,
        "method": "Main$Scanner.next()",
        "variables": {}
    },
    "21": {
        "line_number": 34,
        "method": "Main$Scanner.next()",
        "variables": {}
    },
    "22": {
        "line_number": 40,
        "method": "Main$Scanner.nextInt()",
        "variables": {
            "n": "5",
            "x": "1"
        }
    },
    "23": {
        "line_number": 12,
        "method": "Main.main()",
        "variables": {
            "n": "5",
            "x": "1",
            "y": "3"
        }
    },
    "24": {
        "line_number": 13,
        "method": "Main.main()",
        "variables": {
            "n": "5",
            "x": "1",
            "y": "3"
        }
    },
    "25": {
        "line_number": 14,
        "method": "Main.main()",
        "variables": {
            "n": "5",
            "x": "1",
            "y": "3",
            "i": "0"
        }
    },
    "26": {
        "line_number": 15,
        "method": "Main.main()",
        "variables": {
            "n": "5",
            "x": "1",
            "y": "3",
            "i": "0",
            "j": "1"
        }
    },
    "27": {
        "line_number": 16,
        "method": "Main.main()",
        "variables": {
            "n": "5",
            "x": "1",
            "y": "3",
            "i": "0",
            "j": "1",
            "edge": "1"
        }
    },
    "28": {
        "line_number": 17,
        "method": "Main.main()",
        "variables": {
            "n": "5",
            "x": "1",
            "y": "3",
            "i": "0",
            "j": "1"
        }
    },
    "29": {
        "line_number": 15,
        "method": "Main.main()",
        "variables": {
            "n": "5",
            "x": "1",
            "y": "3",
            "i": "0",
            "j": "2"
        }
    },
    "30": {
        "line_number": 16,
        "method": "Main.main()",
        "variables": {
            "n": "5",
            "x": "1",
            "y": "3",
            "i": "0",
            "j": "2",
            "edge": "2"
        }
    },
    "31": {
        "line_number": 17,
        "method": "Main.main()",
        "variables": {
            "n": "5",
            "x": "1",
            "y": "3",
            "i": "0",
            "j": "2"
        }
    },
    "32": {
        "line_number": 15,
        "method": "Main.main()",
        "variables": {
            "n": "5",
            "x": "1",
            "y": "3",
            "i": "0",
            "j": "3"
        }
    },
    "33": {
        "line_number": 16,
        "method": "Main.main()",
        "variables": {
            "n": "5",
            "x": "1",
            "y": "3",
            "i": "0",
            "j": "3",
            "edge": "2"
        }
    },
    "34": {
        "line_number": 17,
        "method": "Main.main()",
        "variables": {
            "n": "5",
            "x": "1",
            "y": "3",
            "i": "0",
            "j": "3"
        }
    },
    "35": {
        "line_number": 15,
        "method": "Main.main()",
        "variables": {
            "n": "5",
            "x": "1",
            "y": "3",
            "i": "0",
            "j": "4"
        }
    },
    "36": {
        "line_number": 16,
        "method": "Main.main()",
        "variables": {
            "n": "5",
            "x": "1",
            "y": "3",
            "i": "0",
            "j": "4",
            "edge": "3"
        }
    },
    "37": {
        "line_number": 17,
        "method": "Main.main()",
        "variables": {
            "n": "5",
            "x": "1",
            "y": "3",
            "i": "0",
            "j": "4"
        }
    },
    "38": {
        "line_number": 15,
        "method": "Main.main()",
        "variables": {
            "n": "5",
            "x": "1",
            "y": "3",
            "i": "0"
        }
    },
    "39": {
        "line_number": 14,
        "method": "Main.main()",
        "variables": {
            "n": "5",
            "x": "1",
            "y": "3",
            "i": "1"
        }
    },
    "40": {
        "line_number": 15,
        "method": "Main.main()",
        "variables": {
            "n": "5",
            "x": "1",
            "y": "3",
            "i": "1",
            "j": "2"
        }
    },
    "41": {
        "line_number": 16,
        "method": "Main.main()",
        "variables": {
            "n": "5",
            "x": "1",
            "y": "3",
            "i": "1",
            "j": "2",
            "edge": "1"
        }
    },
    "42": {
        "line_number": 17,
        "method": "Main.main()",
        "variables": {
            "n": "5",
            "x": "1",
            "y": "3",
            "i": "1",
            "j": "2"
        }
    },
    "43": {
        "line_number": 15,
        "method": "Main.main()",
        "variables": {
            "n": "5",
            "x": "1",
            "y": "3",
            "i": "1",
            "j": "3"
        }
    },
    "44": {
        "line_number": 16,
        "method": "Main.main()",
        "variables": {
            "n": "5",
            "x": "1",
            "y": "3",
            "i": "1",
            "j": "3",
            "edge": "1"
        }
    },
    "45": {
        "line_number": 17,
        "method": "Main.main()",
        "variables": {
            "n": "5",
            "x": "1",
            "y": "3",
            "i": "1",
            "j": "3"
        }
    },
    "46": {
        "line_number": 15,
        "method": "Main.main()",
        "variables": {
            "n": "5",
            "x": "1",
            "y": "3",
            "i": "1",
            "j": "4"
        }
    },
    "47": {
        "line_number": 16,
        "method": "Main.main()",
        "variables": {
            "n": "5",
            "x": "1",
            "y": "3",
            "i": "1",
            "j": "4",
            "edge": "2"
        }
    },
    "48": {
        "line_number": 17,
        "method": "Main.main()",
        "variables": {
            "n": "5",
            "x": "1",
            "y": "3",
            "i": "1",
            "j": "4"
        }
    },
    "49": {
        "line_number": 15,
        "method": "Main.main()",
        "variables": {
            "n": "5",
            "x": "1",
            "y": "3",
            "i": "1"
        }
    },
    "50": {
        "line_number": 14,
        "method": "Main.main()",
        "variables": {
            "n": "5",
            "x": "1",
            "y": "3",
            "i": "2"
        }
    },
    "51": {
        "line_number": 15,
        "method": "Main.main()",
        "variables": {
            "n": "5",
            "x": "1",
            "y": "3",
            "i": "2",
            "j": "3"
        }
    },
    "52": {
        "line_number": 16,
        "method": "Main.main()",
        "variables": {
            "n": "5",
            "x": "1",
            "y": "3",
            "i": "2",
            "j": "3",
            "edge": "1"
        }
    },
    "53": {
        "line_number": 17,
        "method": "Main.main()",
        "variables": {
            "n": "5",
            "x": "1",
            "y": "3",
            "i": "2",
            "j": "3"
        }
    },
    "54": {
        "line_number": 15,
        "method": "Main.main()",
        "variables": {
            "n": "5",
            "x": "1",
            "y": "3",
            "i": "2",
            "j": "4"
        }
    },
    "55": {
        "line_number": 16,
        "method": "Main.main()",
        "variables": {
            "n": "5",
            "x": "1",
            "y": "3",
            "i": "2",
            "j": "4",
            "edge": "2"
        }
    },
    "56": {
        "line_number": 17,
        "method": "Main.main()",
        "variables": {
            "n": "5",
            "x": "1",
            "y": "3",
            "i": "2",
            "j": "4"
        }
    },
    "57": {
        "line_number": 15,
        "method": "Main.main()",
        "variables": {
            "n": "5",
            "x": "1",
            "y": "3",
            "i": "2"
        }
    },
    "58": {
        "line_number": 14,
        "method": "Main.main()",
        "variables": {
            "n": "5",
            "x": "1",
            "y": "3",
            "i": "3"
        }
    },
    "59": {
        "line_number": 15,
        "method": "Main.main()",
        "variables": {
            "n": "5",
            "x": "1",
            "y": "3",
            "i": "3",
            "j": "4"
        }
    },
    "60": {
        "line_number": 16,
        "method": "Main.main()",
        "variables": {
            "n": "5",
            "x": "1",
            "y": "3",
            "i": "3",
            "j": "4",
            "edge": "1"
        }
    },
    "61": {
        "line_number": 17,
        "method": "Main.main()",
        "variables": {
            "n": "5",
            "x": "1",
            "y": "3",
            "i": "3",
            "j": "4"
        }
    },
    "62": {
        "line_number": 15,
        "method": "Main.main()",
        "variables": {
            "n": "5",
            "x": "1",
            "y": "3",
            "i": "3"
        }
    },
    "63": {
        "line_number": 14,
        "method": "Main.main()",
        "variables": {
            "n": "5",
            "x": "1",
            "y": "3",
            "i": "4"
        }
    },
    "64": {
        "line_number": 15,
        "method": "Main.main()",
        "variables": {
            "n": "5",
            "x": "1",
            "y": "3",
            "i": "4"
        }
    },
    "65": {
        "line_number": 14,
        "method": "Main.main()",
        "variables": {
            "n": "5",
            "x": "1",
            "y": "3"
        }
    },
    "66": {
        "line_number": 20,
        "method": "Main.main()",
        "variables": {
            "n": "5",
            "x": "1",
            "y": "3",
            "i": "1"
        }
    },
    "67": {
        "line_number": 21,
        "method": "Main.main()",
        "variables": {
            "n": "5",
            "x": "1",
            "y": "3",
            "i": "1"
        }
    },
    "68": {
        "line_number": 20,
        "method": "Main.main()",
        "variables": {
            "n": "5",
            "x": "1",
            "y": "3",
            "i": "2"
        }
    },
    "69": {
        "line_number": 21,
        "method": "Main.main()",
        "variables": {
            "n": "5",
            "x": "1",
            "y": "3",
            "i": "2"
        }
    },
    "70": {
        "line_number": 20,
        "method": "Main.main()",
        "variables": {
            "n": "5",
            "x": "1",
            "y": "3",
            "i": "3"
        }
    },
    "71": {
        "line_number": 21,
        "method": "Main.main()",
        "variables": {
            "n": "5",
            "x": "1",
            "y": "3",
            "i": "3"
        }
    },
    "72": {
        "line_number": 20,
        "method": "Main.main()",
        "variables": {
            "n": "5",
            "x": "1",
            "y": "3",
            "i": "4"
        }
    },
    "73": {
        "line_number": 21,
        "method": "Main.main()",
        "variables": {
            "n": "5",
            "x": "1",
            "y": "3",
            "i": "4"
        }
    },
    "74": {
        "line_number": 20,
        "method": "Main.main()",
        "variables": {
            "n": "5",
            "x": "1",
            "y": "3"
        }
    },
    "75": {
        "line_number": 23,
        "method": "Main.main()",
        "variables": {
            "n": "5",
            "x": "1",
            "y": "3"
        }
    }
}